Workbook

Sheet Prioritized Backlog
A1: # | B1: Issue | C1: Category | D1: Agent | E1: Priority | F1: Effort | G1: Impact | H1: Sprint | I1: File(s) | J1: Description & Fix | K1: Status
A2: 1 | B2: Remove hardcoded Supabase credentials | C2: Security | D2: Auditor+Security | E2: P0 | F2: S (2h) | G2: Critical | H2: 1 | I2: lib/constants/supabase_config.dart | J2: Supabase URL and anon key are hardcoded in source. The JWT exposes project ref, role, and expiry. Move to --dart-define build flags: const supabaseUrl = String.fromEnvironment('SUPABASE_URL'); const supabaseAnonKey = String.fromEnvironment('SUPABASE_ANON_KEY'); Update build commands and CI accordingly. Add supabase_config.dart to .gitignore if keeping a local dev fallback. | K2: Open
A3: 2 | B3: Server-side bill number generation | C3: Data Integrity | D3: Logic+Arch | E3: P0 | F3: M (6h) | G3: Critical | H3: 1 | I3: lib/services/bill_number_service.dart, Supabase Edge Function (new) | J3: BillNumberService uses an in-memory counter. Two devices can generate the same bill number simultaneously, and dedup on sync silently drops one bill. Fix: Create a Supabase Edge Function or DB sequence that atomically generates bill numbers per business. Call it from completeBill() before saving. Remove client-side counter as primary source. | K3: Open
A4: 3 | B4: Server-side subscription limit enforcement | C4: Security | D4: Logic+Arch | E4: P0 | F4: M (8h) | G4: Critical | H4: 1 | I4: lib/providers/subscription_provider.dart, Supabase RLS/Edge Fn (new) | J4: canAddBill is checked client-side only; trivially bypassable. increment_bill_count RPC runs AFTER bill creation. Fix: Move bill count check to a Supabase Edge Function or RLS policy that rejects inserts when limit is reached. Return error to client if limit exceeded. | K4: Open
A5: 4 | B5: Fix deleteBill() fallback bug | C5: Bug | D5: Auditor | E5: P0 | F5: S (1h) | G5: Critical | H5: 1 | I5: lib/providers/bill_provider.dart (line 600-609) | J5: deleteBill() uses firstWhere with orElse: () => _bills.first. If billNumber not found, it deletes the FIRST bill in the list — wrong bill. Fix: Use firstWhereOrNull pattern; if null, return early without deleting. Code: final bill = _bills.cast<Bill?>().firstWhere((b) => b?.billNumber == billNumber, orElse: () => null); if (bill == null) return; | K5: Open
A6: 5 | B6: Wrap completeBill() in DB transaction | C6: Data Integrity | D6: Logic+Arch | E6: P0 | F6: M (6h) | G6: Critical | H6: 1 | I6: lib/providers/bill_provider.dart (line 381-527) | J6: completeBill() saves the bill, THEN decrements stock, THEN updates credit. If app crashes between steps, data is inconsistent. Fix: Use Supabase RPC function that atomically: (1) saves bill, (2) decrements stock, (3) updates credit, (4) increments bill count. If any step fails, all roll back. | K6: Open
A7: 6 | B7: Prevent negative stock on decrement | C7: Data Integrity | D7: Logic | E7: P0 | F7: S (2h) | G7: Critical | H7: 1 | I7: lib/providers/product_provider.dart — decrementStock() | J7: decrementStock() does not validate resulting stock >= 0. A product with 5 units can have 10 sold. Fix: Add validation: if (product.stockQuantity - quantity < 0) throw InsufficientStockException(); Also handle batch-level stock check for pharmacy products. | K7: Open
A8: 7 | B8: Add PIN rate limiting | C8: Security | D8: Security | E8: P0 | F8: S (3h) | G8: Critical | H8: 1 | I8: lib/providers/user_provider.dart — login() | J8: 4-digit PIN with static salt "billmaster", no lockout. 10K combinations brute-forceable in milliseconds. Fix: (1) Track failed attempts per user. (2) Lock account for 30s after 3 failures, 5min after 5, permanent after 10. (3) Show remaining attempts to user. (4) Long-term: migrate to 6-digit PIN or biometric. | K8: Open
A9: 8 | B9: Add error handling to syncFromDb() | C9: Bug | D9: Auditor | E9: P0 | F9: S (2h) | G9: High | H9: 1 | I9: lib/providers/bill_provider.dart (line 578-598) | J9: syncFromDb() catches ALL exceptions with empty catch block. Network failures, auth expiry, malformed data — all invisible. Fix: (1) Log the error. (2) Differentiate network vs auth vs parse errors. (3) Show user-facing message on auth expiry. (4) Retry with backoff on network failure. | K9: Open
A10: 9 | B10: Fix batch decrement silent success | C10: Bug | D10: Logic | E10: P0 | F10: S (2h) | G10: High | H10: 1 | I10: lib/providers/product_provider.dart — decrementStock() | J10: decrementStock with batchId: if batch not found, silently decrements main product stock without batch adjustment. Fix: If batchId provided but batch not found, throw an error or log a warning. Don't silently fall through. | K10: Open
A11: 10 | B11: Make all model fields immutable | C11: Code Quality | D11: Auditor | E11: P1 | F11: L (2d) | G11: High | H11: 2 | I11: lib/models/product.dart, customer.dart, supplier.dart, line_item.dart, serial_number.dart, job_card.dart | J11: Product.stockQuantity, Customer.outstandingBalance/advanceBalance, Supplier.outstandingPayable, LineItem.quantity/discountPercent, SerialNumber.status/billId, JobLineItem.quantity/unitPrice are mutable. State can change without notifyListeners(). Fix: Make all fields final. Add copyWith() where missing. Update providers to create new instances instead of mutating. | K11: Open
A12: 11 | B12: Add GST rounding to 2 decimal places | C12: Business Logic | D12: Logic | E12: P1 | F12: S (2h) | G12: High | H12: 2 | I12: lib/services/gst_calculator.dart | J12: Floating-point arithmetic accumulates rounding errors. Indian invoicing requires amounts rounded to nearest paisa. Fix: Add explicit rounding after every calculation: (value * 100).round() / 100. Apply in cgst(), sgst(), igst(), taxableAmount(), grandTotal(). | K12: Open
A13: 12 | B13: Track GST breakdown on returns | C13: Business Logic | D13: Logic | E13: P1 | F13: M (4h) | G13: High | H13: 2 | I13: lib/models/return_line_item.dart, sales_return.dart | J13: ReturnLineItem.refundAmount is a lump sum without CGST/SGST/IGST breakdown. GSTR-1 filing requires reversed tax amounts separately. Fix: Add cgst, sgst, igst fields to ReturnLineItem and SalesReturn. Calculate from original bill's tax rates during return creation. | K13: Open
... A66: 65 | B66: Add page numbers to PDF invoices | C66: Feature | D66: UX | E66: P3 | F66: S (1h) | G66: Low | H66: 6 | I66: lib/services/pdf_invoice_service.dart | J66: Generated PDFs have no page numbers. Multi-page invoices are hard to organize. Fix: Add "Page X of Y" footer to generated PDFs. | K66: Open

Sheet Sprint Plan
A1: Sprint | B1: Focus | C1: Duration | D1: Items | E1: Key Deliverables | F1: Effort Estimate
A2: Sprint 1 | B2: Critical Fixes | C2: Week 1-2 | D2: #1-#9 | E2: Supabase creds secured, server-side bill numbers, transaction wrapping, deleteBill bug fixed, negative stock prevented, PIN rate limiting, error handling | F2: ~32 hours
A3: Sprint 2 | B3: Data Integrity & Quality | C3: Week 3-4 | D3: #10-#22 | E3: Immutable models, GST rounding, return GST tracking, RLS policies, encrypted storage, crash reporting, global error handler, retry logic | F3: ~6 days
A4: Sprint 3 | B4: Architecture & Performance | C4: Week 5-6 | D4: #23-#31 | E4: Use case layer, repository pattern, pagination on all lists, CashBook optimization, lazy tabs, loading skeletons, pull-to-refresh, undo support | F4: ~2.5 weeks
A5: Sprint 4 | B5: UX & Testing | C5: Week 7-8 | D5: #32-#41 | E5: Accessibility (Semantics), Hindi language support, integration tests, provider tests, onboarding flow, search on all screens, sorting options | F5: ~2.5 weeks
A6: Sprint 5 | B6: Schema & Polish | C6: Week 9-11 | D6: #42-#50 | E6: Relational DB migration, invoice payment linkage, dark mode, CSV security, cert pinning, backups, keyboard shortcuts, report exports | F6: ~3 weeks
A7: Sprint 6+ | B7: Long-term Polish | C7: Week 12+ | D7: #51-#65 | E7: Voice search, model equality, toString, ticket enum, notification fixes, vendor cache, accessibility indicators, temp cleanup, CSV limits | F7: ~2 weeks

Sheet Summary
A1: BillReady 2.0 — Audit Summary
A3: Issues by Priority
A4: Priority | B4: Count | C4: Total Effort
A5: P0 — Critical | B5: =COUNTIF('Prioritized Backlog'!E:E,"P0") -> 9 | C5: ~32 hours
A6: P1 — Important | B6: =COUNTIF('Prioritized Backlog'!E:E,"P1") -> 22 | C6: ~7 weeks
A7: P2 — Nice to Have | B7: =COUNTIF('Prioritized Backlog'!E:E,"P2") -> 19 | C7: ~5 weeks
A8: P3 — Polish | B8: =COUNTIF('Prioritized Backlog'!E:E,"P3") -> 15 | C8: ~2 weeks
A9: TOTAL | B9: =SUM(B5:B8) -> 65 | C9: ~18 weeks
A11: Issues by Category | D11: Issues by Agent Source
A12: Category | B12: Count | D12: Agent | E12: Count
A13: Security | B13: =COUNTIF('Prioritized Backlog'!C:C,"Security") -> 9 | D13: Code Auditor | E13: =COUNTIF('Prioritized Backlog'!D:D,"*Auditor*") -> 16
A14: Data Integrity | B14: =COUNTIF('Prioritized Backlog'!C:C,"Data Integrity") -> 3 | D14: Architecture | E14: =COUNTIF('Prioritized Backlog'!D:D,"*Arch*") -> 7
A15: Bug | B15: =COUNTIF('Prioritized Backlog'!C:C,"Bug") -> 5 | D15: UI/UX Design | E15: =COUNTIF('Prioritized Backlog'!D:D,"*UX*") -> 16
A16: Business Logic | B16: =COUNTIF('Prioritized Backlog'!C:C,"Business Logic") -> 5 | D16: Workflow & Logic | E16: =COUNTIF('Prioritized Backlog'!D:D,"*Logic*") -> 13
A17: Code Quality | B17: =COUNTIF('Prioritized Backlog'!C:C,"Code Quality") -> 10 | D17: Security & Performance | E17: =COUNTIF('Prioritized Backlog'!D:D,"*Security*") -> 14
A18: Architecture | B18: =COUNTIF('Prioritized Backlog'!C:C,"Architecture") -> 3
A19: Performance | B19: =COUNTIF('Prioritized Backlog'!C:C,"Performance") -> 7
A20: UX | B20: =COUNTIF('Prioritized Backlog'!C:C,"UX") -> 11
A21: Accessibility | B21: =COUNTIF('Prioritized Backlog'!C:C,"Accessibility") -> 2
A22: Testing | B22: =COUNTIF('Prioritized Backlog'!C:C,"Testing") -> 2
A23: Reliability | B23: =COUNTIF('Prioritized Backlog'!C:C,"Reliability") -> 4
A24: Feature | B24: =COUNTIF('Prioritized Backlog'!C:C,"Feature") -> 4
A27: App Health Score
A28: Current Score | B28: 5.5 / 10
A29: After Sprint 1 | B29: 7.0 / 10
A30: After Sprint 3 | B30: 8.5 / 10
A31: Target (Sprint 5+) | B31: 9.0+ / 10
